README.md
setup.py
matrixbz/__init__.py
matrixbz/bot.py
matrixbz/decorators.py
matrixbz.egg-info/PKG-INFO
matrixbz.egg-info/SOURCES.txt
matrixbz.egg-info/dependency_links.txt
matrixbz.egg-info/not-zip-safe
matrixbz.egg-info/requires.txt
matrixbz.egg-info/top_level.txt
matrixbz/auth/__init__.py
matrixbz/cache/__init__.py
matrixbz/cache/decorators.py
matrixbz/response/__init__.py