Metadata-Version: 2.1
Name: matrixbz
Version: 0.0.2
Summary: UNKNOWN
Home-page: https://decentralabs.io
Author-email: hi@decentralabs.io
License: AGPLv3
Platform: UNKNOWN
